MANIFEST.in
README.rst
setup.cfg
setup.py
daynight2geojson/__init__.py
daynight2geojson/daynight2geojson.py
daynight2geojson.egg-info/PKG-INFO
daynight2geojson.egg-info/SOURCES.txt
daynight2geojson.egg-info/dependency_links.txt
daynight2geojson.egg-info/requires.txt
daynight2geojson.egg-info/top_level.txt
test/__init__.py
test/daynighttesting.py