Metadata-Version: 1.1
Name: daynight2geojson
Version: 0.1
Summary: Get day and night global geometry and dumps to a GeoJSON file. Builded on top of Matplotlib Basemap Toolkit Library.
Home-page: https://github.com/GeographicaGS/daynight2geojson
Author: Cayetano Benavent
Author-email: cayetano.benavent@geographica.gs
License: GPLv2
Keywords: night GIS matplotlib basemap geojson
Platform: UNKNOWN
Classifier: Development Status :: 4 - Beta
Classifier: Intended Audience :: Developers
Classifier: License :: OSI Approved :: GNU General Public License v2 (GPLv2)
Classifier: Programming Language :: Python :: 2.7
Classifier: Operating System :: OS Independent
Classifier: Topic :: Scientific/Engineering :: GIS
